{
    "name": "Shield +3",
    "type": "weapon",
    "img": "icons/equipment/shield/heater-wooden-brown-notched.webp",
    "system": {
        "description": {
            "value": "AC +2.<br><br>While holding this shield, you gain a bonus to your AC determined by the shield's rarity.  This bonus is in addition to the shield's normal bonus to AC.  Additionally, you can add this bonus to attack and damage rolls made using the shield as a weapon.",
            "chat": "",
            "unidentified": ""
        },
        "source": "Core Rules",
        "weight": "6",
        "price": {
            "value": 0,
            "denomination": "gp"
        },
        "rarity": "legendary",
        "weaponType": "shield",
        "attribute": "str",
        "actionType": "other",
        "range": {
            "value": "0",
            "long": "0",
            "units": "ft"
        },
        "critical": {
            "threshold": null,
            "damage": ""
        },
        "attackBonus": "3",
        "damage": {
            "parts": [
                [
                    " + 3",
                    ""
                ]
            ],
            "versatile": ""
        },
        "formula": "",
        "save": {
            "attribute": "",
            "dc": null,
            "scaling": "spell"
        },
        "properties": {
            "amm": false,
            "fin": false,
            "foc": false,
            "hvy": false,
            "lgt": false,
            "lod": false,
            "rch": false,
            "spc": false,
            "thr": false,
            "two": false,
            "una": false,
            "ver": false
        },
        "showInAttacks": false
    },
    "_id": "LUYSMPQKBNKOAICT"
}